__init__.py
yellowdog_client/__init__.py
yellowdog_client/_version.py
yellowdog_client/client_collection.py
yellowdog_client/platform_client.py
yellowdog_client/account/__init__.py
yellowdog_client/account/account_client.py
yellowdog_client/account/account_client_impl.py
yellowdog_client/account/account_service_proxy.py
yellowdog_client/account/keyring_client.py
yellowdog_client/account/keyring_client_impl.py
yellowdog_client/account/keyring_service_proxy.py
yellowdog_client/cloud_info/__init__.py
yellowdog_client/cloud_info/cloud_info_client.py
yellowdog_client/cloud_info/cloud_info_client_impl.py
yellowdog_client/cloud_info/cloud_info_proxy.py
yellowdog_client/common/__init__.py
yellowdog_client/common/closeable.py
yellowdog_client/common/countdown_event.py
yellowdog_client/common/iso_datetime.py
yellowdog_client/common/pagination.py
yellowdog_client/common/proxy.py
yellowdog_client/common/search_client.py
yellowdog_client/common/slice_iterator.py
yellowdog_client/common/synchronized_predicated_runner.py
yellowdog_client/common/user_agent.py
yellowdog_client/common/credentials/__init__.py
yellowdog_client/common/credentials/api_key_authentication_headers_provider.py
yellowdog_client/common/decorators/__init__.py
yellowdog_client/common/decorators/dispatcher.py
yellowdog_client/common/json/__init__.py
yellowdog_client/common/server_sent_events/__init__.py
yellowdog_client/common/server_sent_events/delegated_subscription_event_listener.py
yellowdog_client/common/server_sent_events/subscription.py
yellowdog_client/common/server_sent_events/subscription_event_listener.py
yellowdog_client/common/server_sent_events/subscription_manager.py
yellowdog_client/common/server_sent_events/tracking_subscription_event_listener.py
yellowdog_client/common/server_sent_events/sse4python/__init__.py
yellowdog_client/common/server_sent_events/sse4python/event_source.py
yellowdog_client/common/server_sent_events/sse4python/event_source_state.py
yellowdog_sdk-11.6.0.dist-info/licenses/LICENSE
yellowdog_sdk-11.6.0.dist-info/METADATA
yellowdog_sdk-11.6.0.dist-info/WHEEL
yellowdog_sdk-11.6.0.dist-info/top_level.txt
yellowdog_sdk-11.6.0.dist-info/RECORD
