Metadata-Version: 2.4
Name: yellowdog-sdk
Version: 11.6.0
Summary: SDK for the YellowDog Platform
Author-email: YellowDog Limited <support@yellowdog.co>
Project-URL: Homepage, https://yellowdog.co
Project-URL: Source, https://github.com/yellowdog/yellowdog-sdk-python-public
Classifier: Operating System :: OS Independent
Classifier: Programming Language :: Python :: 3
Classifier: Programming Language :: Python :: 3.7
Classifier: Programming Language :: Python :: 3.8
Classifier: Programming Language :: Python :: 3.9
Classifier: Programming Language :: Python :: 3.10
Classifier: Programming Language :: Python :: 3.11
Classifier: Programming Language :: Python :: 3.12
Classifier: Programming Language :: Python :: 3.13
Classifier: Topic :: Software Development :: Libraries :: Python Modules
Classifier: Intended Audience :: Developers
Classifier: Programming Language :: Python
Classifier: License :: OSI Approved :: Apache Software License
Requires-Python: >=3.7
License-File: LICENSE
Requires-Dist: jsons<2,>=1.4.0
Requires-Dist: requests<3,>=2.25.0
Requires-Dist: urllib3<2,>=1.26.0; python_version < "3.12"
Requires-Dist: urllib3<3,>=2.0.0; python_version >= "3.12"
Requires-Dist: python-dispatch==0.2.2
Requires-Dist: cancel-token==0.1.6
Requires-Dist: isodate<1,>=0.6.1
Provides-Extra: tests
Requires-Dist: pytest==8.3.3; extra == "tests"
Requires-Dist: pytest-httpserver==1.0.8; extra == "tests"
Requires-Dist: typing_compat==0.1.0; extra == "tests"
Requires-Dist: busypie==0.5.1; extra == "tests"
Provides-Extra: docs
Requires-Dist: Sphinx==7.4.7; extra == "docs"
Requires-Dist: sphinx-autodoc-typehints==1.12.0; extra == "docs"
Requires-Dist: sphinx-automodapi==0.13; extra == "docs"
Provides-Extra: deploy
Requires-Dist: twine==3.3.0; extra == "deploy"
Dynamic: license-file
